tidecv/__init__.py
tidecv/ap.py
tidecv/data.py
tidecv/datasets.py
tidecv/functions.py
tidecv/plotting.py
tidecv/quantify.py
tidecv/errors/error.py
tidecv/errors/main_errors.py
tidecv/errors/qualifiers.py
tidecv-1.0.1.dist-info/LICENSE
tidecv-1.0.1.dist-info/METADATA
tidecv-1.0.1.dist-info/WHEEL
tidecv-1.0.1.dist-info/top_level.txt
tidecv-1.0.1.dist-info/RECORD
