Metadata-Version: 2.1
Name: tidecv
Version: 1.0.1
Summary: A General Toolbox for Identifying ObjectDetection Errors
Home-page: https://github.com/dbolya/tide
Author: Daniel Bolya
Author-email: dbolya@gatech.edu
License: MIT
Platform: UNKNOWN
Classifier: License :: OSI Approved :: MIT License
Classifier: Programming Language :: Python :: 3
Classifier: Programming Language :: Python :: 3.6
Classifier: Operating System :: OS Independent
Requires-Python: >=3.6
Requires-Dist: appdirs
Requires-Dist: numpy
Requires-Dist: pycocotools
Requires-Dist: opencv-python
Requires-Dist: seaborn
Requires-Dist: pandas
Requires-Dist: matplotlib
